{
  "version": "2.0.0",
  "generated_at": "2026-06-02T00:00:00Z",
  "count": 19,
  "items": [
    {
      "persona_id": "developer",
      "name": "Software Developer",
      "default_domain": "engineering",
      "preferred_agents": ["engineering.code-reviewer", "engineering.tdd-guide", "engineering.architect"],
      "preferred_tools": ["filesystem.read", "shell.readonly", "code_graph.query"],
      "vocabulary_aliases": { "PR": "pull request", "CI": "continuous integration", "deploy": "deployment" },
      "budget_bias": "standard",
      "default_output_format": "code_with_explanation",
      "disclaimer_level": "none",
      "description": "Software developer focused on code quality, testing, and architecture."
    },
    {
      "persona_id": "architect",
      "name": "Software Architect",
      "default_domain": "engineering.architecture",
      "preferred_agents": ["engineering.architect", "data-ai.rag-engineer", "platform.devops-engineer"],
      "preferred_tools": ["filesystem.read", "code_graph.query"],
      "vocabulary_aliases": { "system": "distributed system", "scale": "horizontal scaling" },
      "budget_bias": "expanded",
      "default_output_format": "decision_record",
      "disclaimer_level": "none",
      "description": "System architect focused on design decisions, trade-offs, and scalability."
    },
    {
      "persona_id": "devops",
      "name": "DevOps / Platform Engineer",
      "default_domain": "platform",
      "preferred_agents": ["platform.devops-engineer", "platform.ci-cd-engineer", "platform.observability-engineer"],
      "preferred_tools": ["shell.readonly", "filesystem.read"],
      "vocabulary_aliases": { "ship": "deploy to production", "infra": "infrastructure" },
      "budget_bias": "standard",
      "default_output_format": "runbook",
      "disclaimer_level": "none",
      "description": "DevOps engineer focused on infrastructure, CI/CD, and observability."
    },
    {
      "persona_id": "qa-engineer",
      "name": "QA / Test Engineer",
      "default_domain": "engineering",
      "preferred_agents": ["engineering.tdd-guide", "engineering.e2e-runner", "data-ai.eval-engineer"],
      "preferred_tools": ["filesystem.read", "shell.readonly"],
      "vocabulary_aliases": { "coverage": "test coverage", "regression": "regression test" },
      "budget_bias": "standard",
      "default_output_format": "test_plan",
      "disclaimer_level": "none",
      "description": "QA engineer focused on test strategy, automation, and quality gates."
    },
    {
      "persona_id": "product-manager",
      "name": "Product Manager",
      "default_domain": "product-business",
      "preferred_agents": [
        "product-business.product-manager",
        "product-business.feature-prioritizer",
        "research.deep-researcher"
      ],
      "preferred_tools": ["filesystem.read"],
      "vocabulary_aliases": {
        "ship": "launch feature",
        "metrics": "product analytics",
        "OKR": "objective and key result"
      },
      "budget_bias": "standard",
      "default_output_format": "product_brief",
      "disclaimer_level": "none",
      "description": "Product manager focused on prioritization, roadmap, and user research."
    },
    {
      "persona_id": "cto",
      "name": "Chief Technology Officer",
      "default_domain": "engineering",
      "preferred_agents": ["product-business.cto-advisor", "engineering.architect", "platform.cloud-architect"],
      "preferred_tools": ["filesystem.read"],
      "vocabulary_aliases": { "tech debt": "technical debt", "platform": "technology platform" },
      "budget_bias": "expanded",
      "default_output_format": "executive_summary",
      "disclaimer_level": "none",
      "description": "CTO focused on technology strategy, team structure, and engineering excellence."
    },
    {
      "persona_id": "ceo",
      "name": "Chief Executive Officer",
      "default_domain": "startup-ops",
      "preferred_agents": ["startup-ops.ceo-rethink", "product-business.ceo-advisor", "research.deep-researcher"],
      "preferred_tools": ["filesystem.read"],
      "vocabulary_aliases": {
        "burn": "monthly burn rate",
        "runway": "cash runway months",
        "PMF": "product-market fit"
      },
      "budget_bias": "expanded",
      "default_output_format": "executive_summary",
      "disclaimer_level": "none",
      "description": "CEO focused on strategy, product direction, and company execution."
    },
    {
      "persona_id": "cfo",
      "name": "Chief Financial Officer",
      "default_domain": "finance",
      "preferred_agents": ["product-business.cfo-advisor", "finance.financial-analyst", "finance.forecasting-analyst"],
      "preferred_tools": ["filesystem.read"],
      "vocabulary_aliases": {
        "runway": "cash runway months",
        "burn": "monthly burn rate",
        "ARR": "annual recurring revenue",
        "EBITDA": "earnings before interest taxes depreciation amortization"
      },
      "budget_bias": "expanded",
      "default_output_format": "structured_report",
      "disclaimer_level": "financial",
      "description": "CFO focused on financial strategy, forecasting, and board-level reporting."
    },
    {
      "persona_id": "marketer",
      "name": "Marketing Professional",
      "default_domain": "marketing",
      "preferred_agents": ["marketing.marketing-strategist", "marketing.content-marketer", "marketing.seo-analyst"],
      "preferred_tools": ["filesystem.read", "filesystem.write"],
      "vocabulary_aliases": {
        "MQL": "marketing qualified lead",
        "CTR": "click-through rate",
        "CAC": "customer acquisition cost"
      },
      "budget_bias": "standard",
      "default_output_format": "marketing_brief",
      "disclaimer_level": "none",
      "description": "Marketing professional focused on content, campaigns, SEO, and growth."
    },
    {
      "persona_id": "sales-rep",
      "name": "Sales Representative",
      "default_domain": "sales",
      "preferred_agents": ["sales.sales-strategist", "sales.pipeline-analyst", "sales.proposal-generator"],
      "preferred_tools": ["filesystem.read", "filesystem.write"],
      "vocabulary_aliases": {
        "ACV": "annual contract value",
        "ICP": "ideal customer profile",
        "POC": "proof of concept"
      },
      "budget_bias": "standard",
      "default_output_format": "proposal",
      "disclaimer_level": "none",
      "description": "Sales rep focused on pipeline, proposals, and deal strategy."
    },
    {
      "persona_id": "hr-manager",
      "name": "HR Manager",
      "default_domain": "hr",
      "preferred_agents": ["hr.hiring-manager", "hr.onboarding-coordinator", "hr.performance-reviewer"],
      "preferred_tools": ["filesystem.read", "filesystem.write"],
      "vocabulary_aliases": { "HC": "headcount", "PIP": "performance improvement plan" },
      "budget_bias": "standard",
      "default_output_format": "hr_document",
      "disclaimer_level": "employment_law",
      "description": "HR manager focused on hiring, onboarding, and people operations."
    },
    {
      "persona_id": "legal-counsel",
      "name": "Legal Counsel",
      "default_domain": "legal-compliance",
      "preferred_agents": [
        "legal-compliance.contract-reviewer",
        "legal-compliance.compliance-checker",
        "legal-compliance.privacy-advisor"
      ],
      "preferred_tools": ["filesystem.read"],
      "vocabulary_aliases": {
        "ToS": "terms of service",
        "DPA": "data processing agreement",
        "NDA": "non-disclosure agreement"
      },
      "budget_bias": "expanded",
      "default_output_format": "risk_summary",
      "disclaimer_level": "legal",
      "description": "Legal counsel focused on contracts, compliance, and risk. Not legal advice."
    },
    {
      "persona_id": "designer",
      "name": "UX/UI Designer",
      "default_domain": "design-content",
      "preferred_agents": [
        "design-content.ui-ux-designer",
        "design-content.accessibility-auditor",
        "design-content.brand-strategist"
      ],
      "preferred_tools": ["filesystem.read", "filesystem.write"],
      "vocabulary_aliases": { "DS": "design system", "a11y": "accessibility", "HCD": "human-centered design" },
      "budget_bias": "standard",
      "default_output_format": "design_spec",
      "disclaimer_level": "none",
      "description": "UX/UI designer focused on user experience, accessibility, and visual design."
    },
    {
      "persona_id": "technical-writer",
      "name": "Technical Writer",
      "default_domain": "design-content",
      "preferred_agents": ["design-content.technical-writer", "engineering.docs-updater"],
      "preferred_tools": ["filesystem.read", "filesystem.write"],
      "vocabulary_aliases": { "API doc": "API documentation", "KB": "knowledge base" },
      "budget_bias": "standard",
      "default_output_format": "documentation",
      "disclaimer_level": "none",
      "description": "Technical writer focused on documentation, API guides, and knowledge bases."
    },
    {
      "persona_id": "data-analyst",
      "name": "Data Analyst",
      "default_domain": "data-ai",
      "preferred_agents": ["data-ai.data-analyst", "data-ai.rag-engineer", "data-ai.eval-engineer"],
      "preferred_tools": ["filesystem.read", "shell.readonly"],
      "vocabulary_aliases": { "KPI": "key performance indicator", "DAU": "daily active users" },
      "budget_bias": "standard",
      "default_output_format": "analysis_report",
      "disclaimer_level": "none",
      "description": "Data analyst focused on metrics, experimentation, and insight generation."
    },
    {
      "persona_id": "researcher",
      "name": "Researcher",
      "default_domain": "research",
      "preferred_agents": ["research.deep-researcher", "research.literature-reviewer", "research.market-researcher"],
      "preferred_tools": ["filesystem.read"],
      "vocabulary_aliases": { "lit review": "literature review", "SOTA": "state of the art" },
      "budget_bias": "expanded",
      "default_output_format": "research_brief",
      "disclaimer_level": "none",
      "description": "Researcher focused on deep-web research, literature review, and synthesis."
    },
    {
      "persona_id": "operations-manager",
      "name": "Operations Manager",
      "default_domain": "product-business",
      "preferred_agents": [
        "product-business.operations-planner",
        "manufacturing.supply-chain-analyst",
        "platform.incident-responder"
      ],
      "preferred_tools": ["filesystem.read", "filesystem.write"],
      "vocabulary_aliases": { "OPS": "operations", "SLA": "service level agreement" },
      "budget_bias": "standard",
      "default_output_format": "operational_plan",
      "disclaimer_level": "none",
      "description": "Operations manager focused on process, efficiency, and cross-functional coordination."
    },
    {
      "persona_id": "customer-success",
      "name": "Customer Success Manager",
      "default_domain": "product-business",
      "preferred_agents": ["product-business.customer-success-advisor", "sales.account-manager"],
      "preferred_tools": ["filesystem.read", "filesystem.write"],
      "vocabulary_aliases": {
        "NPS": "net promoter score",
        "churn": "customer churn rate",
        "QBR": "quarterly business review"
      },
      "budget_bias": "standard",
      "default_output_format": "customer_brief",
      "disclaimer_level": "none",
      "description": "Customer success manager focused on retention, expansion, and customer health."
    },
    {
      "persona_id": "founder",
      "name": "Founder / Solo Builder",
      "default_domain": "startup-ops",
      "preferred_agents": ["startup-ops.master", "startup-ops.ceo-rethink", "startup-ops.release"],
      "preferred_tools": ["filesystem.read", "filesystem.write"],
      "vocabulary_aliases": {
        "PMF": "product-market fit",
        "MVP": "minimum viable product",
        "runway": "cash runway months"
      },
      "budget_bias": "standard",
      "default_output_format": "actionable_plan",
      "disclaimer_level": "none",
      "description": "Solo founder or small-team builder focused on shipping and learning fast."
    }
  ]
}
